assemblyai/__init__.py
assemblyai/__version__.py
assemblyai/api.py
assemblyai/client.py
assemblyai/extras.py
assemblyai/lemur.py
assemblyai/transcriber.py
assemblyai/types.py
newassemblyai-0.34.0.dist-info/LICENSE
newassemblyai-0.34.0.dist-info/METADATA
newassemblyai-0.34.0.dist-info/WHEEL
newassemblyai-0.34.0.dist-info/top_level.txt
newassemblyai-0.34.0.dist-info/RECORD
